<?xml version="1.0" encoding="utf-8"?>
<resources>
  <string name="enter">Ingresso</string>
  <string name="find">Nome Videocamera</string>
  <string name="findTitle">Ricerca per nome</string>
  <string name="cameraNotFound">Impossibile trovare videocamera indicata</string>
  <string name="live">Dal vivo</string>
  <string name="archive">Archivio</string>
  <string name="edit">Modifica</string>
  <string name="presets">Impostazioni predefinite</string>
  <string name="ptzControl">Controlli PTZ</string>
  <string name="calendar-closeText">Impostare</string>
  <string name="calendar-currentText">Ora</string>
  <string name="calendar-timeOnlyTitle">Scegliere orario</string>
  <string name="calendar-timeText">Orario</string>
  <string name="calendar-hourText">Ore</string>
  <string name="calendar-minuteText">Min.</string>
  <string name="calendar-secondText">Sec.</string>
  <string name="calendar-millisecText">Millisecondi</string>
  <string name="calendar-timezoneText">Fuso orario</string>
  <string name="calendar-dateFormate">dd/MM/yyyy</string>
  <string name="calendar-dayNames-0">Domenica</string>
  <string name="calendar-dayNames-1">Lunedì</string>
  <string name="calendar-dayNames-2">Martedì</string>
  <string name="calendar-dayNames-3">Mercoledì</string>
  <string name="calendar-dayNames-4">Giovedì</string>
  <string name="calendar-dayNames-5">Venerdì</string>
  <string name="calendar-dayNames-6">Sabato</string>
  <string name="calendar-dayNamesMin-0">Dom</string>
  <string name="calendar-dayNamesMin-1">Lun</string>
  <string name="calendar-dayNamesMin-2">Mar</string>
  <string name="calendar-dayNamesMin-3">Mer</string>
  <string name="calendar-dayNamesMin-4">Gio</string>
  <string name="calendar-dayNamesMin-5">Ven</string>
  <string name="calendar-dayNamesMin-6">Sab</string>
  <string name="calendar-dayNamesShort-0">Dom</string>
  <string name="calendar-dayNamesShort-1">Lun</string>
  <string name="calendar-dayNamesShort-2">Mar</string>
  <string name="calendar-dayNamesShort-3">Mer</string>
  <string name="calendar-dayNamesShort-4">Gio</string>
  <string name="calendar-dayNamesShort-5">Ven</string>
  <string name="calendar-dayNamesShort-6">Sab</string>
  <string name="calendar-monthNames-0">Gennaio</string>
  <string name="calendar-monthNames-1">Febbraio</string>
  <string name="calendar-monthNames-2">Marzo</string>
  <string name="calendar-monthNames-3">Aprile</string>
  <string name="calendar-monthNames-4">Maggio</string>
  <string name="calendar-monthNames-5">Giugno</string>
  <string name="calendar-monthNames-6">Lug</string>
  <string name="calendar-monthNames-7">Agosto</string>
  <string name="calendar-monthNames-8">Settembre</string>
  <string name="calendar-monthNames-9">Ottobre</string>
  <string name="calendar-monthNames-10">Novembre</string>
  <string name="calendar-monthNames-11">Dicembre</string>
  <string name="calendar-monthNamesShort-0">Gen</string>
  <string name="calendar-monthNamesShort-1">Feb</string>
  <string name="calendar-monthNamesShort-2">Mar</string>
  <string name="calendar-monthNamesShort-3">Apr</string>
  <string name="calendar-monthNamesShort-4">Maggio</string>
  <string name="calendar-monthNamesShort-5">Giugno</string>
  <string name="calendar-monthNamesShort-6">Luglio</string>
  <string name="calendar-monthNamesShort-7">Ago</string>
  <string name="calendar-monthNamesShort-8">Sett</string>
  <string name="calendar-monthNamesShort-9">Ott</string>
  <string name="calendar-monthNamesShort-10">Nov</string>
  <string name="calendar-monthNamesShort-11">Dic</string>
  <string name="calendar-nextText">Successivo</string>
  <string name="calendar-prevText">Precedente</string>
  <string name="prevFrame">Fotogramma precedente</string>
  <string name="nextFrame">Frame successivo</string>
  <string name="prevInt">Intervallo precedente</string>
  <string name="nextInt">Intervallo successivo</string>
  <string name="error">Errore</string>
  <string name="warn">Attenzione</string>
  <string name="info">Informazioni</string>
  <string name="escapePress">Premuto Esc, probabilmente non tutti gli oggetti sono caricati, provare di nuovo.</string>
  <string name="running">Client ITV in esecuzione</string>
  <string name="logged">Connesso</string>
  <string name="archiveNotFound">Non è possibile posizionarsi sull'archivio.</string>
  <string name="notAllPresetsRecieved">Non tutte le impostazioni predefinite ricevute, provare di nuovo</string>
  <string name="notAllDegreesRecieved">Non tutti i gradi di libertà ottenuti, provare di nuovo</string>
  <string name="notTelemetryRecieved">Dispositivo di telemetria non ricevuto, riprovare</string>
  <string name="timeoutException">La connessione al server è mantenuta oltre il timeout. Possibile fallimento del comando, riprovare.</string>
  <string name="notGetArchive">Archivio non trovato, riprovare.</string>
  <string name="notGetUUID">UUID non ricevuto</string>
  <string name="cameraWithNameNotFound">Impossibile trovare videocamera indicata</string>
  <string name="choseDate">Scegliere data</string>
  <string name="badDate">Archivio non trovato</string>
  <string name="notSupported">Non supportato, aggiornare il browser</string>
  <string name="wndMsg">Finestra messaggio</string>
  <string name="clear">Cancellare</string>
  <string name="serverOnline">Server is online</string>
  <string name="serverOffline">Server is not responding</string>
  <string name="calendar-timeFormat">HH:mm:ss</string>
  <string name="calendar-firstDay">1</string>
  <string name="logout">Change user</string>
  <string name="export">Export</string>
  <string name="exportFormat">Format</string>
  <string name="exportComment">Comment</string>
  <string name="preferences-hint">Preferences</string>
  <string name="preferences-disconnectInactive">Disconnect stream when inactive</string>
  <string name="preferences.layout.default">Layout selected by default</string>
  <string name="preferences.layout.none">Not set</string>
  <string name="preferences.stream.default">Video stream selected by default</string>
  <string name="preferences.stream.auto">Auto</string>
  <string name="preferences.stream.low">Low quality</string>
  <string name="preferences.stream.high">High quality</string>
</resources>
